{
  "football": [
    {
      "matchup": "Chiefs @ Bills",
      "market": "Spread",
      "line": "KC -3.5",
      "odds": "-110",
      "startTime": "8:20 PM ET"
    },
    {
      "matchup": "Cowboys @ Eagles",
      "market": "Total",
      "line": "O 49.5",
      "odds": "-108",
      "startTime": "4:25 PM ET"
    },
    {
      "matchup": "Packers @ Bears",
      "market": "Moneyline",
      "line": "GB -122",
      "odds": "-122",
      "startTime": "1:00 PM ET"
    }
  ],
  "basketball": [
    {
      "matchup": "Lakers @ Warriors",
      "market": "Player Pts",
      "line": "LeBron 28.5",
      "odds": "-102",
      "startTime": "10:00 PM ET"
    },
    {
      "matchup": "Celtics @ Heat",
      "market": "Spread",
      "line": "BOS -4.5",
      "odds": "-112",
      "startTime": "7:30 PM ET"
    }
  ],
  "baseball": [
    {
      "matchup": "Yankees @ Astros",
      "market": "Moneyline",
      "line": "NYY -118",
      "odds": "-118",
      "startTime": "7:10 PM ET"
    },
    {
      "matchup": "Dodgers @ Mariners",
      "market": "Total",
      "line": "O 8.5",
      "odds": "-105",
      "startTime": "9:40 PM ET"
    }
  ]
}
